pyautocorpus.cpython-310-x86_64-linux-gnu.so
pyautocorpus-0.1.12.dist-info/top_level.txt
pyautocorpus-0.1.12.dist-info/RECORD
pyautocorpus-0.1.12.dist-info/WHEEL
pyautocorpus-0.1.12.dist-info/METADATA
pyautocorpus.libs/libpcre-9513aab5.so.1.2.0
