Metadata-Version: 2.1
Name: pyautocorpus
Version: 0.1.12
Home-page: https://github.com/seanmacavaney/pyautocorpus
Author: Sean MacAvaney
Author-email: sean.macavaney@gmail.com
Classifier: License :: OSI Approved :: MIT License
Requires-Python: >=3.7
